dmlc_tracker/__init__.py
dmlc_tracker/kubernetes.py
dmlc_tracker/launcher.py
dmlc_tracker/local.py
dmlc_tracker/mesos.py
dmlc_tracker/mpi.py
dmlc_tracker/opts.py
dmlc_tracker/sge.py
dmlc_tracker/slurm.py
dmlc_tracker/ssh.py
dmlc_tracker/submit.py
dmlc_tracker/tracker.py
dmlc_tracker/yarn.py
mxnet/COMMIT_HASH
mxnet/MKLML_LICENSE
mxnet/__init__.py
mxnet/attribute.py
mxnet/autograd.py
mxnet/base.py
mxnet/callback.py
mxnet/context.py
mxnet/engine.py
mxnet/executor.py
mxnet/executor_manager.py
mxnet/initializer.py
mxnet/io.py
mxnet/kvstore.py
mxnet/kvstore_server.py
mxnet/libgfortran.so.3
mxnet/libinfo.py
mxnet/libiomp5.so
mxnet/libmkldnn.so.0
mxnet/libmklml_intel.so
mxnet/libmxnet.so
mxnet/libquadmath.so.0
mxnet/log.py
mxnet/lr_scheduler.py
mxnet/metric.py
mxnet/misc.py
mxnet/model.py
mxnet/monitor.py
mxnet/name.py
mxnet/ndarray_doc.py
mxnet/operator.py
mxnet/optimizer.py
mxnet/profiler.py
mxnet/random.py
mxnet/recordio.py
mxnet/registry.py
mxnet/rtc.py
mxnet/symbol_doc.py
mxnet/test_utils.py
mxnet/torch.py
mxnet/visualization.py
mxnet/_ctypes/__init__.py
mxnet/_ctypes/ndarray.py
mxnet/_ctypes/symbol.py
mxnet/_cy2/__init__.py
mxnet/_cy3/__init__.py
mxnet/contrib/__init__.py
mxnet/contrib/autograd.py
mxnet/contrib/io.py
mxnet/contrib/ndarray.py
mxnet/contrib/quantization.py
mxnet/contrib/symbol.py
mxnet/contrib/tensorboard.py
mxnet/contrib/onnx/__init__.py
mxnet/contrib/onnx/_import/__init__.py
mxnet/contrib/onnx/_import/import_helper.py
mxnet/contrib/onnx/_import/import_model.py
mxnet/contrib/onnx/_import/import_onnx.py
mxnet/contrib/onnx/_import/op_translations.py
mxnet/contrib/onnx/_import/translation_utils.py
mxnet/contrib/text/__init__.py
mxnet/contrib/text/_constants.py
mxnet/contrib/text/embedding.py
mxnet/contrib/text/utils.py
mxnet/contrib/text/vocab.py
mxnet/gluon/__init__.py
mxnet/gluon/block.py
mxnet/gluon/loss.py
mxnet/gluon/parameter.py
mxnet/gluon/trainer.py
mxnet_cu75mkl-1.2.1.post1.dist-info/METADATA
mxnet_cu75mkl-1.2.1.post1.dist-info/RECORD
mxnet_cu75mkl-1.2.1.post1.dist-info/WHEEL
mxnet_cu75mkl-1.2.1.post1.dist-info/top_level.txt
