Metadata-Version: 2.1
Name: mxnet-cu75mkl
Version: 1.2.1.post1
Summary: MXNet is an ultra-scalable deep learning framework. This version uses CUDA-7.5 and MKLDNN.
Home-page: https://github.com/apache/incubator-mxnet
Author: UNKNOWN
Author-email: UNKNOWN
License: Apache 2.0
Platform: UNKNOWN
Classifier: Development Status :: 5 - Production/Stable
Classifier: Intended Audience :: Developers
Classifier: Intended Audience :: Education
Classifier: Intended Audience :: Science/Research
Classifier: License :: OSI Approved :: Apache Software License
Classifier: Programming Language :: C++
Classifier: Programming Language :: Cython
Classifier: Programming Language :: Other
Classifier: Programming Language :: Perl
Classifier: Programming Language :: Python
Classifier: Programming Language :: Python :: 2.7
Classifier: Programming Language :: Python :: 3.4
Classifier: Programming Language :: Python :: 3.5
Classifier: Programming Language :: Python :: 3.6
Classifier: Programming Language :: Python :: Implementation :: CPython
Classifier: Topic :: Scientific/Engineering
Classifier: Topic :: Scientific/Engineering :: Artificial Intelligence
Classifier: Topic :: Scientific/Engineering :: Mathematics
Classifier: Topic :: Software Development
Classifier: Topic :: Software Development :: Libraries
Classifier: Topic :: Software Development :: Libraries :: Python Modules
Requires-Dist: numpy (<1.15.0,>=1.8.2)
Requires-Dist: requests (<2.19.0,>=2.18.4)
Requires-Dist: graphviz (<0.9.0,>=0.8.1)
